{
  "metadata" : {
    "identifier" : "https://www.nettruyenio.com/truyen-tranh/het-nhu-han-quang-gap-nang-gat-282470",
    "title" : "Hệt Như Hàn Quang Gặp Nắng Gắt - Chapter 234",
    "subtitle" : null,
    "author" : null,
    "narrator" : null,
    "language" : "vi",
    "description" : null,
    "publisher" : "N/A",
    "subject" : null,
    "modified" : null,
    "published" : "2023-06-22",
    "duration" : 0,
    "abridged" : false,
    "conformsTo" : "https://readium.org/webpub-manifest/profiles/divina",
    "numberOfPages" : 456,
    "readingProgression" : "ttb",
    "belongsTo" : null,
    "presentation" : {
      "fit" : "width",
      "overflow" : "scrolled",
      "continuous" : true
    },
    "@type" : null,
    "schema:license" : null
  },
  "links" : [ {
    "rel" : "self",
    "href" : "https://raw.githubusercontent.com/thuvienonline40/book_storage_collection/main/comic_manifest.json",
    "type" : "application/divina+json"
  } ],
  "readingOrder" : [ {
    "href" : "https://raw.githubusercontent.com/quetcccd/comic_storage3/main/IMAGE/IMAGE_f39d5cbcb673c52213444728b63e0558_c2e3f823005eabecc74dea35b512bac1_54292e7b9287b51158718d9b786a6106.jpg",
    "type" : "image/jpeg",
    "bitrate" : 0,
    "duration" : 0,
    "title" : null,
    "properties" : null,
    "alternate" : [ {
      "href" : "https://i551.ntcdntempv26.com/data/images/28247/796038/001.jpg?data=net",
      "type" : "image/jpeg",
      "bitrate" : 0,
      "duration" : 0,
      "title" : null,
      "properties" : null,
      "alternate" : null
    } ]
  }, {
    "href" : "https://raw.githubusercontent.com/quetcccd/comic_storage3/main/IMAGE/IMAGE_f39d5cbcb673c52213444728b63e0558_c2e3f823005eabecc74dea35b512bac1_5ecfff3e4518641dca3d2e9b9d3f7345.jpg",
    "type" : "image/jpeg",
    "bitrate" : 0,
    "duration" : 0,
    "title" : null,
    "properties" : null,
    "alternate" : [ {
      "href" : "https://i551.ntcdntempv26.com/data/images/28247/796038/002.jpg?data=net",
      "type" : "image/jpeg",
      "bitrate" : 0,
      "duration" : 0,
      "title" : null,
      "properties" : null,
      "alternate" : null
    } ]
  }, {
    "href" : "https://raw.githubusercontent.com/quetcccd/comic_storage3/main/IMAGE/IMAGE_f39d5cbcb673c52213444728b63e0558_c2e3f823005eabecc74dea35b512bac1_143ee2b310642a58233243ddca90818f.jpg",
    "type" : "image/jpeg",
    "bitrate" : 0,
    "duration" : 0,
    "title" : null,
    "properties" : null,
    "alternate" : [ {
      "href" : "https://i551.ntcdntempv26.com/data/images/28247/796038/003.jpg?data=net",
      "type" : "image/jpeg",
      "bitrate" : 0,
      "duration" : 0,
      "title" : null,
      "properties" : null,
      "alternate" : null
    } ]
  }, {
    "href" : "https://raw.githubusercontent.com/quetcccd/comic_storage3/main/IMAGE/IMAGE_f39d5cbcb673c52213444728b63e0558_c2e3f823005eabecc74dea35b512bac1_f05426642d3cf63611100831ed97fc7c.jpg",
    "type" : "image/jpeg",
    "bitrate" : 0,
    "duration" : 0,
    "title" : null,
    "properties" : null,
    "alternate" : [ {
      "href" : "https://i551.ntcdntempv26.com/data/images/28247/796038/004.jpg?data=net",
      "type" : "image/jpeg",
      "bitrate" : 0,
      "duration" : 0,
      "title" : null,
      "properties" : null,
      "alternate" : null
    } ]
  }, {
    "href" : "https://raw.githubusercontent.com/quetcccd/comic_storage3/main/IMAGE/IMAGE_f39d5cbcb673c52213444728b63e0558_c2e3f823005eabecc74dea35b512bac1_d179f33545fa521dc68d6f4c4e91e4f3.jpg",
    "type" : "image/jpeg",
    "bitrate" : 0,
    "duration" : 0,
    "title" : null,
    "properties" : null,
    "alternate" : [ {
      "href" : "https://i551.ntcdntempv26.com/data/images/28247/796038/005.jpg?data=net",
      "type" : "image/jpeg",
      "bitrate" : 0,
      "duration" : 0,
      "title" : null,
      "properties" : null,
      "alternate" : null
    } ]
  }, {
    "href" : "https://raw.githubusercontent.com/quetcccd/comic_storage3/main/IMAGE/IMAGE_f39d5cbcb673c52213444728b63e0558_c2e3f823005eabecc74dea35b512bac1_fe7e16c795bb88bd5e4b670b71286103.jpg",
    "type" : "image/jpeg",
    "bitrate" : 0,
    "duration" : 0,
    "title" : null,
    "properties" : null,
    "alternate" : [ {
      "href" : "https://i551.ntcdntempv26.com/data/images/28247/796038/006.jpg?data=net",
      "type" : "image/jpeg",
      "bitrate" : 0,
      "duration" : 0,
      "title" : null,
      "properties" : null,
      "alternate" : null
    } ]
  }, {
    "href" : "https://raw.githubusercontent.com/quetcccd/comic_storage3/main/IMAGE/IMAGE_f39d5cbcb673c52213444728b63e0558_c2e3f823005eabecc74dea35b512bac1_65006ec751e61c1200c2d712aab58f51.jpg",
    "type" : "image/jpeg",
    "bitrate" : 0,
    "duration" : 0,
    "title" : null,
    "properties" : null,
    "alternate" : [ {
      "href" : "https://i551.ntcdntempv26.com/data/images/28247/796038/007.jpg?data=net",
      "type" : "image/jpeg",
      "bitrate" : 0,
      "duration" : 0,
      "title" : null,
      "properties" : null,
      "alternate" : null
    } ]
  }, {
    "href" : "https://raw.githubusercontent.com/quetcccd/comic_storage3/main/IMAGE/IMAGE_f39d5cbcb673c52213444728b63e0558_c2e3f823005eabecc74dea35b512bac1_7f70f3ee3be2755e64be22ce1f63355e.jpg",
    "type" : "image/jpeg",
    "bitrate" : 0,
    "duration" : 0,
    "title" : null,
    "properties" : null,
    "alternate" : [ {
      "href" : "https://i551.ntcdntempv26.com/data/images/28247/796038/008.jpg?data=net",
      "type" : "image/jpeg",
      "bitrate" : 0,
      "duration" : 0,
      "title" : null,
      "properties" : null,
      "alternate" : null
    } ]
  }, {
    "href" : "https://raw.githubusercontent.com/quetcccd/comic_storage3/main/IMAGE/IMAGE_f39d5cbcb673c52213444728b63e0558_c2e3f823005eabecc74dea35b512bac1_455864f71a0412e4faeee66ba2cf4581.jpg",
    "type" : "image/jpeg",
    "bitrate" : 0,
    "duration" : 0,
    "title" : null,
    "properties" : null,
    "alternate" : [ {
      "href" : "https://i551.ntcdntempv26.com/data/images/28247/796038/009.jpg?data=net",
      "type" : "image/jpeg",
      "bitrate" : 0,
      "duration" : 0,
      "title" : null,
      "properties" : null,
      "alternate" : null
    } ]
  }, {
    "href" : "https://raw.githubusercontent.com/quetcccd/comic_storage3/main/IMAGE/IMAGE_f39d5cbcb673c52213444728b63e0558_c2e3f823005eabecc74dea35b512bac1_af8982cfbd2c8470f78a580695dacc95.jpg",
    "type" : "image/jpeg",
    "bitrate" : 0,
    "duration" : 0,
    "title" : null,
    "properties" : null,
    "alternate" : [ {
      "href" : "https://i551.ntcdntempv26.com/data/images/28247/796038/010.jpg?data=net",
      "type" : "image/jpeg",
      "bitrate" : 0,
      "duration" : 0,
      "title" : null,
      "properties" : null,
      "alternate" : null
    } ]
  }, {
    "href" : "https://raw.githubusercontent.com/quetcccd/comic_storage3/main/IMAGE/IMAGE_f39d5cbcb673c52213444728b63e0558_c2e3f823005eabecc74dea35b512bac1_d66b26287ceac819bd07fd13b846d80e.jpg",
    "type" : "image/jpeg",
    "bitrate" : 0,
    "duration" : 0,
    "title" : null,
    "properties" : null,
    "alternate" : [ {
      "href" : "https://i551.ntcdntempv26.com/data/images/28247/796038/011.jpg?data=net",
      "type" : "image/jpeg",
      "bitrate" : 0,
      "duration" : 0,
      "title" : null,
      "properties" : null,
      "alternate" : null
    } ]
  }, {
    "href" : "https://raw.githubusercontent.com/quetcccd/comic_storage3/main/IMAGE/IMAGE_f39d5cbcb673c52213444728b63e0558_c2e3f823005eabecc74dea35b512bac1_a3a47c6fde4cb8bf9a244927dd854208.jpg",
    "type" : "image/jpeg",
    "bitrate" : 0,
    "duration" : 0,
    "title" : null,
    "properties" : null,
    "alternate" : [ {
      "href" : "https://i551.ntcdntempv26.com/data/images/28247/796038/012.jpg?data=net",
      "type" : "image/jpeg",
      "bitrate" : 0,
      "duration" : 0,
      "title" : null,
      "properties" : null,
      "alternate" : null
    } ]
  }, {
    "href" : "https://raw.githubusercontent.com/quetcccd/comic_storage3/main/IMAGE/IMAGE_f39d5cbcb673c52213444728b63e0558_c2e3f823005eabecc74dea35b512bac1_55524acbeb9a54d16545e130af9256df.jpg",
    "type" : "image/jpeg",
    "bitrate" : 0,
    "duration" : 0,
    "title" : null,
    "properties" : null,
    "alternate" : [ {
      "href" : "https://i551.ntcdntempv26.com/data/images/28247/796038/013.jpg?data=net",
      "type" : "image/jpeg",
      "bitrate" : 0,
      "duration" : 0,
      "title" : null,
      "properties" : null,
      "alternate" : null
    } ]
  }, {
    "href" : "https://raw.githubusercontent.com/quetcccd/comic_storage3/main/IMAGE/IMAGE_f39d5cbcb673c52213444728b63e0558_c2e3f823005eabecc74dea35b512bac1_d0316c98b2086d9dae2d40037c624e7a.jpg",
    "type" : "image/jpeg",
    "bitrate" : 0,
    "duration" : 0,
    "title" : null,
    "properties" : null,
    "alternate" : [ {
      "href" : "https://i551.ntcdntempv26.com/data/images/28247/796038/014.jpg?data=net",
      "type" : "image/jpeg",
      "bitrate" : 0,
      "duration" : 0,
      "title" : null,
      "properties" : null,
      "alternate" : null
    } ]
  }, {
    "href" : "https://raw.githubusercontent.com/quetcccd/comic_storage3/main/IMAGE/IMAGE_f39d5cbcb673c52213444728b63e0558_c2e3f823005eabecc74dea35b512bac1_7a89119f5035b7dd87ffc2c135a67674.jpg",
    "type" : "image/jpeg",
    "bitrate" : 0,
    "duration" : 0,
    "title" : null,
    "properties" : null,
    "alternate" : [ {
      "href" : "https://i551.ntcdntempv26.com/data/images/28247/796038/015.jpg?data=net",
      "type" : "image/jpeg",
      "bitrate" : 0,
      "duration" : 0,
      "title" : null,
      "properties" : null,
      "alternate" : null
    } ]
  }, {
    "href" : "https://raw.githubusercontent.com/quetcccd/comic_storage3/main/IMAGE/IMAGE_f39d5cbcb673c52213444728b63e0558_c2e3f823005eabecc74dea35b512bac1_0a2229da2670733f2fc27b08645b5926.jpg",
    "type" : "image/jpeg",
    "bitrate" : 0,
    "duration" : 0,
    "title" : null,
    "properties" : null,
    "alternate" : [ {
      "href" : "https://i551.ntcdntempv26.com/data/images/28247/796038/016.jpg?data=net",
      "type" : "image/jpeg",
      "bitrate" : 0,
      "duration" : 0,
      "title" : null,
      "properties" : null,
      "alternate" : null
    } ]
  }, {
    "href" : "https://raw.githubusercontent.com/quetcccd/comic_storage3/main/IMAGE/IMAGE_f39d5cbcb673c52213444728b63e0558_c2e3f823005eabecc74dea35b512bac1_635facf64eb25286c2accfff5204213e.jpg",
    "type" : "image/jpeg",
    "bitrate" : 0,
    "duration" : 0,
    "title" : null,
    "properties" : null,
    "alternate" : [ {
      "href" : "https://i551.ntcdntempv26.com/data/images/28247/796038/017.jpg?data=net",
      "type" : "image/jpeg",
      "bitrate" : 0,
      "duration" : 0,
      "title" : null,
      "properties" : null,
      "alternate" : null
    } ]
  }, {
    "href" : "https://raw.githubusercontent.com/quetcccd/comic_storage3/main/IMAGE/IMAGE_f39d5cbcb673c52213444728b63e0558_c2e3f823005eabecc74dea35b512bac1_06806490786d84f9b8c9494674f0354f.jpg",
    "type" : "image/jpeg",
    "bitrate" : 0,
    "duration" : 0,
    "title" : null,
    "properties" : null,
    "alternate" : [ {
      "href" : "https://i551.ntcdntempv26.com/data/images/28247/796038/018.jpg?data=net",
      "type" : "image/jpeg",
      "bitrate" : 0,
      "duration" : 0,
      "title" : null,
      "properties" : null,
      "alternate" : null
    } ]
  }, {
    "href" : "https://raw.githubusercontent.com/quetcccd/comic_storage3/main/IMAGE/IMAGE_f39d5cbcb673c52213444728b63e0558_c2e3f823005eabecc74dea35b512bac1_554d8e9222acc630f5289d319031aac4.jpg",
    "type" : "image/jpeg",
    "bitrate" : 0,
    "duration" : 0,
    "title" : null,
    "properties" : null,
    "alternate" : [ {
      "href" : "https://i551.ntcdntempv26.com/data/images/28247/796038/019.jpg?data=net",
      "type" : "image/jpeg",
      "bitrate" : 0,
      "duration" : 0,
      "title" : null,
      "properties" : null,
      "alternate" : null
    } ]
  }, {
    "href" : "https://raw.githubusercontent.com/quetcccd/comic_storage3/main/IMAGE/IMAGE_f39d5cbcb673c52213444728b63e0558_c2e3f823005eabecc74dea35b512bac1_1cc2c0083ff8885b1da497868ad37d13.jpg",
    "type" : "image/jpeg",
    "bitrate" : 0,
    "duration" : 0,
    "title" : null,
    "properties" : null,
    "alternate" : [ {
      "href" : "https://i551.ntcdntempv26.com/data/images/28247/796038/020.jpg?data=net",
      "type" : "image/jpeg",
      "bitrate" : 0,
      "duration" : 0,
      "title" : null,
      "properties" : null,
      "alternate" : null
    } ]
  }, {
    "href" : "https://raw.githubusercontent.com/quetcccd/comic_storage3/main/IMAGE/IMAGE_f39d5cbcb673c52213444728b63e0558_c2e3f823005eabecc74dea35b512bac1_714903a230a4ccbf2a463713a7bb415e.jpg",
    "type" : "image/jpeg",
    "bitrate" : 0,
    "duration" : 0,
    "title" : null,
    "properties" : null,
    "alternate" : [ {
      "href" : "https://i551.ntcdntempv26.com/data/images/28247/796038/021.jpg?data=net",
      "type" : "image/jpeg",
      "bitrate" : 0,
      "duration" : 0,
      "title" : null,
      "properties" : null,
      "alternate" : null
    } ]
  }, {
    "href" : "https://raw.githubusercontent.com/quetcccd/comic_storage3/main/IMAGE/IMAGE_f39d5cbcb673c52213444728b63e0558_c2e3f823005eabecc74dea35b512bac1_21cb611e096bc118700f602edb59c125.jpg",
    "type" : "image/jpeg",
    "bitrate" : 0,
    "duration" : 0,
    "title" : null,
    "properties" : null,
    "alternate" : [ {
      "href" : "https://i551.ntcdntempv26.com/data/images/28247/796038/022.jpg?data=net",
      "type" : "image/jpeg",
      "bitrate" : 0,
      "duration" : 0,
      "title" : null,
      "properties" : null,
      "alternate" : null
    } ]
  }, {
    "href" : "https://raw.githubusercontent.com/quetcccd/comic_storage3/main/IMAGE/IMAGE_f39d5cbcb673c52213444728b63e0558_c2e3f823005eabecc74dea35b512bac1_188eb0dfb77484a471921d080bc0c872.jpg",
    "type" : "image/jpeg",
    "bitrate" : 0,
    "duration" : 0,
    "title" : null,
    "properties" : null,
    "alternate" : [ {
      "href" : "https://i551.ntcdntempv26.com/data/images/28247/796038/023.jpg?data=net",
      "type" : "image/jpeg",
      "bitrate" : 0,
      "duration" : 0,
      "title" : null,
      "properties" : null,
      "alternate" : null
    } ]
  }, {
    "href" : "https://raw.githubusercontent.com/quetcccd/comic_storage3/main/IMAGE/IMAGE_f39d5cbcb673c52213444728b63e0558_c2e3f823005eabecc74dea35b512bac1_874775943089cb697e36c591a7982e09.jpg",
    "type" : "image/jpeg",
    "bitrate" : 0,
    "duration" : 0,
    "title" : null,
    "properties" : null,
    "alternate" : [ {
      "href" : "https://i551.ntcdntempv26.com/data/images/28247/796038/024.jpg?data=net",
      "type" : "image/jpeg",
      "bitrate" : 0,
      "duration" : 0,
      "title" : null,
      "properties" : null,
      "alternate" : null
    } ]
  }, {
    "href" : "https://raw.githubusercontent.com/quetcccd/comic_storage3/main/IMAGE/IMAGE_f39d5cbcb673c52213444728b63e0558_c2e3f823005eabecc74dea35b512bac1_b09236d7344e7fa455122a096385db55.jpg",
    "type" : "image/jpeg",
    "bitrate" : 0,
    "duration" : 0,
    "title" : null,
    "properties" : null,
    "alternate" : [ {
      "href" : "https://i551.ntcdntempv26.com/data/images/28247/796038/025.jpg?data=net",
      "type" : "image/jpeg",
      "bitrate" : 0,
      "duration" : 0,
      "title" : null,
      "properties" : null,
      "alternate" : null
    } ]
  }, {
    "href" : "https://raw.githubusercontent.com/quetcccd/comic_storage3/main/IMAGE/IMAGE_f39d5cbcb673c52213444728b63e0558_c2e3f823005eabecc74dea35b512bac1_79b75da7bdf85cf1224605712d989aea.jpg",
    "type" : "image/jpeg",
    "bitrate" : 0,
    "duration" : 0,
    "title" : null,
    "properties" : null,
    "alternate" : [ {
      "href" : "https://i551.ntcdntempv26.com/data/images/28247/796038/026.jpg?data=net",
      "type" : "image/jpeg",
      "bitrate" : 0,
      "duration" : 0,
      "title" : null,
      "properties" : null,
      "alternate" : null
    } ]
  }, {
    "href" : "https://raw.githubusercontent.com/quetcccd/comic_storage3/main/IMAGE/IMAGE_f39d5cbcb673c52213444728b63e0558_c2e3f823005eabecc74dea35b512bac1_ac2f1de821cfedab6b7901ad64609e00.jpg",
    "type" : "image/jpeg",
    "bitrate" : 0,
    "duration" : 0,
    "title" : null,
    "properties" : null,
    "alternate" : [ {
      "href" : "https://i551.ntcdntempv26.com/data/images/28247/796038/027.jpg?data=net",
      "type" : "image/jpeg",
      "bitrate" : 0,
      "duration" : 0,
      "title" : null,
      "properties" : null,
      "alternate" : null
    } ]
  }, {
    "href" : "https://raw.githubusercontent.com/quetcccd/comic_storage3/main/IMAGE/IMAGE_f39d5cbcb673c52213444728b63e0558_c2e3f823005eabecc74dea35b512bac1_34034886107fd90e69b1fc8942b9f6a8.jpg",
    "type" : "image/jpeg",
    "bitrate" : 0,
    "duration" : 0,
    "title" : null,
    "properties" : null,
    "alternate" : [ {
      "href" : "https://i551.ntcdntempv26.com/data/images/28247/796038/028.jpg?data=net",
      "type" : "image/jpeg",
      "bitrate" : 0,
      "duration" : 0,
      "title" : null,
      "properties" : null,
      "alternate" : null
    } ]
  }, {
    "href" : "https://raw.githubusercontent.com/quetcccd/comic_storage3/main/IMAGE/IMAGE_f39d5cbcb673c52213444728b63e0558_c2e3f823005eabecc74dea35b512bac1_f40d1a46b5160373b3d84c07c18fa0dd.jpg",
    "type" : "image/jpeg",
    "bitrate" : 0,
    "duration" : 0,
    "title" : null,
    "properties" : null,
    "alternate" : [ {
      "href" : "https://i551.ntcdntempv26.com/data/images/28247/796038/029.jpg?data=net",
      "type" : "image/jpeg",
      "bitrate" : 0,
      "duration" : 0,
      "title" : null,
      "properties" : null,
      "alternate" : null
    } ]
  }, {
    "href" : "https://raw.githubusercontent.com/quetcccd/comic_storage3/main/IMAGE/IMAGE_f39d5cbcb673c52213444728b63e0558_c2e3f823005eabecc74dea35b512bac1_562ba2448acb370321934b07900c14c5.jpg",
    "type" : "image/jpeg",
    "bitrate" : 0,
    "duration" : 0,
    "title" : null,
    "properties" : null,
    "alternate" : [ {
      "href" : "https://i551.ntcdntempv26.com/data/images/28247/796038/030.jpg?data=net",
      "type" : "image/jpeg",
      "bitrate" : 0,
      "duration" : 0,
      "title" : null,
      "properties" : null,
      "alternate" : null
    } ]
  }, {
    "href" : "https://raw.githubusercontent.com/quetcccd/comic_storage3/main/IMAGE/IMAGE_f39d5cbcb673c52213444728b63e0558_c2e3f823005eabecc74dea35b512bac1_cca3fc5ab71d5095333db3a8861f71c2.jpg",
    "type" : "image/jpeg",
    "bitrate" : 0,
    "duration" : 0,
    "title" : null,
    "properties" : null,
    "alternate" : [ {
      "href" : "https://i551.ntcdntempv26.com/data/images/28247/796038/031.jpg?data=net",
      "type" : "image/jpeg",
      "bitrate" : 0,
      "duration" : 0,
      "title" : null,
      "properties" : null,
      "alternate" : null
    } ]
  }, {
    "href" : "https://raw.githubusercontent.com/quetcccd/comic_storage3/main/IMAGE/IMAGE_f39d5cbcb673c52213444728b63e0558_c2e3f823005eabecc74dea35b512bac1_80840ad7253c779c41c6d669df69b063.jpg",
    "type" : "image/jpeg",
    "bitrate" : 0,
    "duration" : 0,
    "title" : null,
    "properties" : null,
    "alternate" : [ {
      "href" : "https://i551.ntcdntempv26.com/data/images/28247/796038/032.jpg?data=net",
      "type" : "image/jpeg",
      "bitrate" : 0,
      "duration" : 0,
      "title" : null,
      "properties" : null,
      "alternate" : null
    } ]
  }, {
    "href" : "https://raw.githubusercontent.com/quetcccd/comic_storage3/main/IMAGE/IMAGE_f39d5cbcb673c52213444728b63e0558_c2e3f823005eabecc74dea35b512bac1_efedc6feaa18d05c5008ebff99d08fa2.jpg",
    "type" : "image/jpeg",
    "bitrate" : 0,
    "duration" : 0,
    "title" : null,
    "properties" : null,
    "alternate" : [ {
      "href" : "https://i551.ntcdntempv26.com/data/images/28247/796038/033.jpg?data=net",
      "type" : "image/jpeg",
      "bitrate" : 0,
      "duration" : 0,
      "title" : null,
      "properties" : null,
      "alternate" : null
    } ]
  }, {
    "href" : "https://raw.githubusercontent.com/quetcccd/comic_storage3/main/IMAGE/IMAGE_f39d5cbcb673c52213444728b63e0558_c2e3f823005eabecc74dea35b512bac1_5baed9bc59c6b0b18445f95171849436.jpg",
    "type" : "image/jpeg",
    "bitrate" : 0,
    "duration" : 0,
    "title" : null,
    "properties" : null,
    "alternate" : [ {
      "href" : "https://i551.ntcdntempv26.com/data/images/28247/796038/034.jpg?data=net",
      "type" : "image/jpeg",
      "bitrate" : 0,
      "duration" : 0,
      "title" : null,
      "properties" : null,
      "alternate" : null
    } ]
  }, {
    "href" : "https://raw.githubusercontent.com/quetcccd/comic_storage3/main/IMAGE/IMAGE_f39d5cbcb673c52213444728b63e0558_c2e3f823005eabecc74dea35b512bac1_30d67b54868b3f7440fc7cf9bbb4d970.jpg",
    "type" : "image/jpeg",
    "bitrate" : 0,
    "duration" : 0,
    "title" : null,
    "properties" : null,
    "alternate" : [ {
      "href" : "https://i551.ntcdntempv26.com/data/images/28247/796038/035.jpg?data=net",
      "type" : "image/jpeg",
      "bitrate" : 0,
      "duration" : 0,
      "title" : null,
      "properties" : null,
      "alternate" : null
    } ]
  }, {
    "href" : "https://raw.githubusercontent.com/quetcccd/comic_storage3/main/IMAGE/IMAGE_f39d5cbcb673c52213444728b63e0558_c2e3f823005eabecc74dea35b512bac1_d35d7f9554ff4974f8decf7930d4d0fe.jpg",
    "type" : "image/jpeg",
    "bitrate" : 0,
    "duration" : 0,
    "title" : null,
    "properties" : null,
    "alternate" : [ {
      "href" : "https://i551.ntcdntempv26.com/data/images/28247/796038/036.jpg?data=net",
      "type" : "image/jpeg",
      "bitrate" : 0,
      "duration" : 0,
      "title" : null,
      "properties" : null,
      "alternate" : null
    } ]
  }, {
    "href" : "https://raw.githubusercontent.com/quetcccd/comic_storage3/main/IMAGE/IMAGE_f39d5cbcb673c52213444728b63e0558_c2e3f823005eabecc74dea35b512bac1_9bbb79739273c7c0333824ac5f51ba1b.jpg",
    "type" : "image/jpeg",
    "bitrate" : 0,
    "duration" : 0,
    "title" : null,
    "properties" : null,
    "alternate" : [ {
      "href" : "https://i551.ntcdntempv26.com/data/images/28247/796038/037.jpg?data=net",
      "type" : "image/jpeg",
      "bitrate" : 0,
      "duration" : 0,
      "title" : null,
      "properties" : null,
      "alternate" : null
    } ]
  } ],
  "toc" : null,
  "@context" : "https://readium.org/webpub-manifest/context.jsonld"
}