{
  "metadata" : {
    "identifier" : "https://www.nettruyenio.com/truyen-tranh/hen-ho-roi-hay-yeu-72214",
    "title" : "Hẹn Hò Rồi Hãy Yêu - Chapter 15",
    "subtitle" : null,
    "author" : null,
    "narrator" : null,
    "language" : "vi",
    "description" : null,
    "publisher" : "N/A",
    "subject" : null,
    "modified" : null,
    "published" : "2023-06-22",
    "duration" : 0,
    "abridged" : false,
    "conformsTo" : "https://readium.org/webpub-manifest/profiles/divina",
    "numberOfPages" : 86,
    "readingProgression" : "ttb",
    "belongsTo" : null,
    "presentation" : {
      "fit" : "width",
      "overflow" : "scrolled",
      "continuous" : true
    },
    "@type" : null,
    "schema:license" : null
  },
  "links" : [ {
    "rel" : "self",
    "href" : "https://raw.githubusercontent.com/thuvienonline40/book_storage_collection/main/comic_manifest.json",
    "type" : "application/divina+json"
  } ],
  "readingOrder" : [ {
    "href" : "https://raw.githubusercontent.com/quetcccd/comic_storage3/main/IMAGE/IMAGE_34b82a332a2ef91d16e4b69e0f5bca07_eeb5b77fb89263f894eebe3e491ad38c_d8d140828ef28abd903547815b8ceec7.jpg",
    "type" : "image/jpeg",
    "bitrate" : 0,
    "duration" : 0,
    "title" : null,
    "properties" : null,
    "alternate" : [ {
      "href" : "https://i225.ntcdntempv26.com/data/images/72214/916633/001-24e0c1f.jpg?data=net",
      "type" : "image/jpeg",
      "bitrate" : 0,
      "duration" : 0,
      "title" : null,
      "properties" : null,
      "alternate" : null
    } ]
  }, {
    "href" : "https://raw.githubusercontent.com/quetcccd/comic_storage3/main/IMAGE/IMAGE_34b82a332a2ef91d16e4b69e0f5bca07_eeb5b77fb89263f894eebe3e491ad38c_b42e46cfbc7a29c90f33ebe0a91cf065.jpg",
    "type" : "image/jpeg",
    "bitrate" : 0,
    "duration" : 0,
    "title" : null,
    "properties" : null,
    "alternate" : [ {
      "href" : "https://i225.ntcdntempv26.com/data/images/72214/916633/002-de554ef.jpg?data=net",
      "type" : "image/jpeg",
      "bitrate" : 0,
      "duration" : 0,
      "title" : null,
      "properties" : null,
      "alternate" : null
    } ]
  }, {
    "href" : "https://raw.githubusercontent.com/quetcccd/comic_storage3/main/IMAGE/IMAGE_34b82a332a2ef91d16e4b69e0f5bca07_eeb5b77fb89263f894eebe3e491ad38c_762d027a627f80c3a826f61acc65ccb7.jpg",
    "type" : "image/jpeg",
    "bitrate" : 0,
    "duration" : 0,
    "title" : null,
    "properties" : null,
    "alternate" : [ {
      "href" : "https://i225.ntcdntempv26.com/data/images/72214/916633/003-3664ac7.jpg?data=net",
      "type" : "image/jpeg",
      "bitrate" : 0,
      "duration" : 0,
      "title" : null,
      "properties" : null,
      "alternate" : null
    } ]
  }, {
    "href" : "https://raw.githubusercontent.com/quetcccd/comic_storage3/main/IMAGE/IMAGE_34b82a332a2ef91d16e4b69e0f5bca07_eeb5b77fb89263f894eebe3e491ad38c_f787b8001d550e6b2f7fdb08e3763707.jpg",
    "type" : "image/jpeg",
    "bitrate" : 0,
    "duration" : 0,
    "title" : null,
    "properties" : null,
    "alternate" : [ {
      "href" : "https://i225.ntcdntempv26.com/data/images/72214/916633/004-066f7b8.jpg?data=net",
      "type" : "image/jpeg",
      "bitrate" : 0,
      "duration" : 0,
      "title" : null,
      "properties" : null,
      "alternate" : null
    } ]
  }, {
    "href" : "https://raw.githubusercontent.com/quetcccd/comic_storage3/main/IMAGE/IMAGE_34b82a332a2ef91d16e4b69e0f5bca07_eeb5b77fb89263f894eebe3e491ad38c_3e69dd8394bbad79ed1c21cd3aa8f323.jpg",
    "type" : "image/jpeg",
    "bitrate" : 0,
    "duration" : 0,
    "title" : null,
    "properties" : null,
    "alternate" : [ {
      "href" : "https://i225.ntcdntempv26.com/data/images/72214/916633/005-67c999f.jpg?data=net",
      "type" : "image/jpeg",
      "bitrate" : 0,
      "duration" : 0,
      "title" : null,
      "properties" : null,
      "alternate" : null
    } ]
  }, {
    "href" : "https://raw.githubusercontent.com/quetcccd/comic_storage3/main/IMAGE/IMAGE_34b82a332a2ef91d16e4b69e0f5bca07_eeb5b77fb89263f894eebe3e491ad38c_52eae61bea9fbae35bf3726c470a1391.jpg",
    "type" : "image/jpeg",
    "bitrate" : 0,
    "duration" : 0,
    "title" : null,
    "properties" : null,
    "alternate" : [ {
      "href" : "https://i225.ntcdntempv26.com/data/images/72214/916633/006-edfc00e.jpg?data=net",
      "type" : "image/jpeg",
      "bitrate" : 0,
      "duration" : 0,
      "title" : null,
      "properties" : null,
      "alternate" : null
    } ]
  }, {
    "href" : "https://raw.githubusercontent.com/quetcccd/comic_storage3/main/IMAGE/IMAGE_34b82a332a2ef91d16e4b69e0f5bca07_eeb5b77fb89263f894eebe3e491ad38c_38c5f54543588b4854f777d5cc50f647.jpg",
    "type" : "image/jpeg",
    "bitrate" : 0,
    "duration" : 0,
    "title" : null,
    "properties" : null,
    "alternate" : [ {
      "href" : "https://i225.ntcdntempv26.com/data/images/72214/916633/007-2a0fc20.jpg?data=net",
      "type" : "image/jpeg",
      "bitrate" : 0,
      "duration" : 0,
      "title" : null,
      "properties" : null,
      "alternate" : null
    } ]
  }, {
    "href" : "https://raw.githubusercontent.com/quetcccd/comic_storage3/main/IMAGE/IMAGE_34b82a332a2ef91d16e4b69e0f5bca07_eeb5b77fb89263f894eebe3e491ad38c_e848544185ab386603bb8f137878c77b.jpg",
    "type" : "image/jpeg",
    "bitrate" : 0,
    "duration" : 0,
    "title" : null,
    "properties" : null,
    "alternate" : [ {
      "href" : "https://i225.ntcdntempv26.com/data/images/72214/916633/008-69facae.jpg?data=net",
      "type" : "image/jpeg",
      "bitrate" : 0,
      "duration" : 0,
      "title" : null,
      "properties" : null,
      "alternate" : null
    } ]
  }, {
    "href" : "https://raw.githubusercontent.com/quetcccd/comic_storage3/main/IMAGE/IMAGE_34b82a332a2ef91d16e4b69e0f5bca07_eeb5b77fb89263f894eebe3e491ad38c_e3dea97da892d72e86cc76d195e61964.jpg",
    "type" : "image/jpeg",
    "bitrate" : 0,
    "duration" : 0,
    "title" : null,
    "properties" : null,
    "alternate" : [ {
      "href" : "https://i225.ntcdntempv26.com/data/images/72214/916633/009-e87da85.jpg?data=net",
      "type" : "image/jpeg",
      "bitrate" : 0,
      "duration" : 0,
      "title" : null,
      "properties" : null,
      "alternate" : null
    } ]
  }, {
    "href" : "https://raw.githubusercontent.com/quetcccd/comic_storage3/main/IMAGE/IMAGE_34b82a332a2ef91d16e4b69e0f5bca07_eeb5b77fb89263f894eebe3e491ad38c_f1b85b8c8d89ace2519cdfdd4814e43b.jpg",
    "type" : "image/jpeg",
    "bitrate" : 0,
    "duration" : 0,
    "title" : null,
    "properties" : null,
    "alternate" : [ {
      "href" : "https://i225.ntcdntempv26.com/data/images/72214/916633/010-3fe6cad.jpg?data=net",
      "type" : "image/jpeg",
      "bitrate" : 0,
      "duration" : 0,
      "title" : null,
      "properties" : null,
      "alternate" : null
    } ]
  }, {
    "href" : "https://raw.githubusercontent.com/quetcccd/comic_storage3/main/IMAGE/IMAGE_34b82a332a2ef91d16e4b69e0f5bca07_eeb5b77fb89263f894eebe3e491ad38c_039b092fe22d9ee6257496bf7627b72c.jpg",
    "type" : "image/jpeg",
    "bitrate" : 0,
    "duration" : 0,
    "title" : null,
    "properties" : null,
    "alternate" : [ {
      "href" : "https://i225.ntcdntempv26.com/data/images/72214/916633/011-6be5532.jpg?data=net",
      "type" : "image/jpeg",
      "bitrate" : 0,
      "duration" : 0,
      "title" : null,
      "properties" : null,
      "alternate" : null
    } ]
  }, {
    "href" : "https://raw.githubusercontent.com/quetcccd/comic_storage3/main/IMAGE/IMAGE_34b82a332a2ef91d16e4b69e0f5bca07_eeb5b77fb89263f894eebe3e491ad38c_30170d87ae0e98ecbce80830d1e752b3.jpg",
    "type" : "image/jpeg",
    "bitrate" : 0,
    "duration" : 0,
    "title" : null,
    "properties" : null,
    "alternate" : [ {
      "href" : "https://i225.ntcdntempv26.com/data/images/72214/916633/012-6d810aa.jpg?data=net",
      "type" : "image/jpeg",
      "bitrate" : 0,
      "duration" : 0,
      "title" : null,
      "properties" : null,
      "alternate" : null
    } ]
  }, {
    "href" : "https://raw.githubusercontent.com/quetcccd/comic_storage3/main/IMAGE/IMAGE_34b82a332a2ef91d16e4b69e0f5bca07_eeb5b77fb89263f894eebe3e491ad38c_3e8b82292d37d992949c9be00e29f366.jpg",
    "type" : "image/jpeg",
    "bitrate" : 0,
    "duration" : 0,
    "title" : null,
    "properties" : null,
    "alternate" : [ {
      "href" : "https://i225.ntcdntempv26.com/data/images/72214/916633/013-b12dd35.jpg?data=net",
      "type" : "image/jpeg",
      "bitrate" : 0,
      "duration" : 0,
      "title" : null,
      "properties" : null,
      "alternate" : null
    } ]
  }, {
    "href" : "https://raw.githubusercontent.com/quetcccd/comic_storage3/main/IMAGE/IMAGE_34b82a332a2ef91d16e4b69e0f5bca07_eeb5b77fb89263f894eebe3e491ad38c_85c69c3be29a05ac874b0af358ce0e44.jpg",
    "type" : "image/jpeg",
    "bitrate" : 0,
    "duration" : 0,
    "title" : null,
    "properties" : null,
    "alternate" : [ {
      "href" : "https://i225.ntcdntempv26.com/data/images/72214/916633/014-d6322ad.jpg?data=net",
      "type" : "image/jpeg",
      "bitrate" : 0,
      "duration" : 0,
      "title" : null,
      "properties" : null,
      "alternate" : null
    } ]
  }, {
    "href" : "https://raw.githubusercontent.com/quetcccd/comic_storage3/main/IMAGE/IMAGE_34b82a332a2ef91d16e4b69e0f5bca07_eeb5b77fb89263f894eebe3e491ad38c_f5d5c46f1c85ebd25100a617f85f8097.jpg",
    "type" : "image/jpeg",
    "bitrate" : 0,
    "duration" : 0,
    "title" : null,
    "properties" : null,
    "alternate" : [ {
      "href" : "https://i225.ntcdntempv26.com/data/images/72214/916633/015-da5792a.jpg?data=net",
      "type" : "image/jpeg",
      "bitrate" : 0,
      "duration" : 0,
      "title" : null,
      "properties" : null,
      "alternate" : null
    } ]
  }, {
    "href" : "https://raw.githubusercontent.com/quetcccd/comic_storage3/main/IMAGE/IMAGE_34b82a332a2ef91d16e4b69e0f5bca07_eeb5b77fb89263f894eebe3e491ad38c_bb8c9b022477f020bc5b46a7ae9077c2.jpg",
    "type" : "image/jpeg",
    "bitrate" : 0,
    "duration" : 0,
    "title" : null,
    "properties" : null,
    "alternate" : [ {
      "href" : "https://i225.ntcdntempv26.com/data/images/72214/916633/016-e0240f4.jpg?data=net",
      "type" : "image/jpeg",
      "bitrate" : 0,
      "duration" : 0,
      "title" : null,
      "properties" : null,
      "alternate" : null
    } ]
  }, {
    "href" : "https://raw.githubusercontent.com/quetcccd/comic_storage3/main/IMAGE/IMAGE_34b82a332a2ef91d16e4b69e0f5bca07_eeb5b77fb89263f894eebe3e491ad38c_1d71162cea448f1bca94e5a2eaf522c5.jpg",
    "type" : "image/jpeg",
    "bitrate" : 0,
    "duration" : 0,
    "title" : null,
    "properties" : null,
    "alternate" : [ {
      "href" : "https://i225.ntcdntempv26.com/data/images/72214/916633/017-ef79f32.jpg?data=net",
      "type" : "image/jpeg",
      "bitrate" : 0,
      "duration" : 0,
      "title" : null,
      "properties" : null,
      "alternate" : null
    } ]
  }, {
    "href" : "https://raw.githubusercontent.com/quetcccd/comic_storage3/main/IMAGE/IMAGE_34b82a332a2ef91d16e4b69e0f5bca07_eeb5b77fb89263f894eebe3e491ad38c_05196c6f827bfddaab2793ed70148753.jpg",
    "type" : "image/jpeg",
    "bitrate" : 0,
    "duration" : 0,
    "title" : null,
    "properties" : null,
    "alternate" : [ {
      "href" : "https://i225.ntcdntempv26.com/data/images/72214/916633/018-109e4cb.jpg?data=net",
      "type" : "image/jpeg",
      "bitrate" : 0,
      "duration" : 0,
      "title" : null,
      "properties" : null,
      "alternate" : null
    } ]
  }, {
    "href" : "https://raw.githubusercontent.com/quetcccd/comic_storage3/main/IMAGE/IMAGE_34b82a332a2ef91d16e4b69e0f5bca07_eeb5b77fb89263f894eebe3e491ad38c_81ff138c99c61a95a85ce0942b9e0b3d.jpg",
    "type" : "image/jpeg",
    "bitrate" : 0,
    "duration" : 0,
    "title" : null,
    "properties" : null,
    "alternate" : [ {
      "href" : "https://i225.ntcdntempv26.com/data/images/72214/916633/019-89b57aa.jpg?data=net",
      "type" : "image/jpeg",
      "bitrate" : 0,
      "duration" : 0,
      "title" : null,
      "properties" : null,
      "alternate" : null
    } ]
  }, {
    "href" : "https://raw.githubusercontent.com/quetcccd/comic_storage3/main/IMAGE/IMAGE_34b82a332a2ef91d16e4b69e0f5bca07_eeb5b77fb89263f894eebe3e491ad38c_f4a6f6dcbfad01181f66d2e6025f5239.jpg",
    "type" : "image/jpeg",
    "bitrate" : 0,
    "duration" : 0,
    "title" : null,
    "properties" : null,
    "alternate" : [ {
      "href" : "https://i225.ntcdntempv26.com/data/images/72214/916633/020-871d8fd.jpg?data=net",
      "type" : "image/jpeg",
      "bitrate" : 0,
      "duration" : 0,
      "title" : null,
      "properties" : null,
      "alternate" : null
    } ]
  }, {
    "href" : "https://raw.githubusercontent.com/quetcccd/comic_storage3/main/IMAGE/IMAGE_34b82a332a2ef91d16e4b69e0f5bca07_eeb5b77fb89263f894eebe3e491ad38c_cdbce47a06c2f6b96a892e0bdeb0eb49.jpg",
    "type" : "image/jpeg",
    "bitrate" : 0,
    "duration" : 0,
    "title" : null,
    "properties" : null,
    "alternate" : [ {
      "href" : "https://i225.ntcdntempv26.com/data/images/72214/916633/021-72d9f16.jpg?data=net",
      "type" : "image/jpeg",
      "bitrate" : 0,
      "duration" : 0,
      "title" : null,
      "properties" : null,
      "alternate" : null
    } ]
  }, {
    "href" : "https://raw.githubusercontent.com/quetcccd/comic_storage3/main/IMAGE/IMAGE_34b82a332a2ef91d16e4b69e0f5bca07_eeb5b77fb89263f894eebe3e491ad38c_d9c0f3ddcbc3ba56a3e239545a5c4478.jpg",
    "type" : "image/jpeg",
    "bitrate" : 0,
    "duration" : 0,
    "title" : null,
    "properties" : null,
    "alternate" : [ {
      "href" : "https://i225.ntcdntempv26.com/data/images/72214/916633/022-0b13399.jpg?data=net",
      "type" : "image/jpeg",
      "bitrate" : 0,
      "duration" : 0,
      "title" : null,
      "properties" : null,
      "alternate" : null
    } ]
  }, {
    "href" : "https://raw.githubusercontent.com/quetcccd/comic_storage3/main/IMAGE/IMAGE_34b82a332a2ef91d16e4b69e0f5bca07_eeb5b77fb89263f894eebe3e491ad38c_ea5f84bacc6c6d80e03e3c97c6c1c541.jpg",
    "type" : "image/jpeg",
    "bitrate" : 0,
    "duration" : 0,
    "title" : null,
    "properties" : null,
    "alternate" : [ {
      "href" : "https://i225.ntcdntempv26.com/data/images/72214/916633/023-60946c6.jpg?data=net",
      "type" : "image/jpeg",
      "bitrate" : 0,
      "duration" : 0,
      "title" : null,
      "properties" : null,
      "alternate" : null
    } ]
  }, {
    "href" : "https://raw.githubusercontent.com/quetcccd/comic_storage3/main/IMAGE/IMAGE_34b82a332a2ef91d16e4b69e0f5bca07_eeb5b77fb89263f894eebe3e491ad38c_837ff7d9e903d227d229c213787b6ef2.jpg",
    "type" : "image/jpeg",
    "bitrate" : 0,
    "duration" : 0,
    "title" : null,
    "properties" : null,
    "alternate" : [ {
      "href" : "https://i225.ntcdntempv26.com/data/images/72214/916633/024-3b02dd6.jpg?data=net",
      "type" : "image/jpeg",
      "bitrate" : 0,
      "duration" : 0,
      "title" : null,
      "properties" : null,
      "alternate" : null
    } ]
  }, {
    "href" : "https://raw.githubusercontent.com/quetcccd/comic_storage3/main/IMAGE/IMAGE_34b82a332a2ef91d16e4b69e0f5bca07_eeb5b77fb89263f894eebe3e491ad38c_26902454c2de3046b7ef78a1194d141e.jpg",
    "type" : "image/jpeg",
    "bitrate" : 0,
    "duration" : 0,
    "title" : null,
    "properties" : null,
    "alternate" : [ {
      "href" : "https://i225.ntcdntempv26.com/data/images/72214/916633/025-4c5e211.jpg?data=net",
      "type" : "image/jpeg",
      "bitrate" : 0,
      "duration" : 0,
      "title" : null,
      "properties" : null,
      "alternate" : null
    } ]
  }, {
    "href" : "https://raw.githubusercontent.com/quetcccd/comic_storage3/main/IMAGE/IMAGE_34b82a332a2ef91d16e4b69e0f5bca07_eeb5b77fb89263f894eebe3e491ad38c_cb05b77d9ad1c0c533c08a8c0f4a6749.jpg",
    "type" : "image/jpeg",
    "bitrate" : 0,
    "duration" : 0,
    "title" : null,
    "properties" : null,
    "alternate" : [ {
      "href" : "https://i225.ntcdntempv26.com/data/images/72214/916633/026-7321d71.jpg?data=net",
      "type" : "image/jpeg",
      "bitrate" : 0,
      "duration" : 0,
      "title" : null,
      "properties" : null,
      "alternate" : null
    } ]
  }, {
    "href" : "https://raw.githubusercontent.com/quetcccd/comic_storage3/main/IMAGE/IMAGE_34b82a332a2ef91d16e4b69e0f5bca07_eeb5b77fb89263f894eebe3e491ad38c_ee38f16c027b4cf1484d4bd3f49d72ed.jpg",
    "type" : "image/jpeg",
    "bitrate" : 0,
    "duration" : 0,
    "title" : null,
    "properties" : null,
    "alternate" : [ {
      "href" : "https://i225.ntcdntempv26.com/data/images/72214/916633/027-a8302cc.jpg?data=net",
      "type" : "image/jpeg",
      "bitrate" : 0,
      "duration" : 0,
      "title" : null,
      "properties" : null,
      "alternate" : null
    } ]
  }, {
    "href" : "https://raw.githubusercontent.com/quetcccd/comic_storage3/main/IMAGE/IMAGE_34b82a332a2ef91d16e4b69e0f5bca07_eeb5b77fb89263f894eebe3e491ad38c_74c72f89e019a9c0906ee6342c156912.jpg",
    "type" : "image/jpeg",
    "bitrate" : 0,
    "duration" : 0,
    "title" : null,
    "properties" : null,
    "alternate" : [ {
      "href" : "https://i225.ntcdntempv26.com/data/images/72214/916633/028-5059e94.jpg?data=net",
      "type" : "image/jpeg",
      "bitrate" : 0,
      "duration" : 0,
      "title" : null,
      "properties" : null,
      "alternate" : null
    } ]
  }, {
    "href" : "https://raw.githubusercontent.com/quetcccd/comic_storage3/main/IMAGE/IMAGE_34b82a332a2ef91d16e4b69e0f5bca07_eeb5b77fb89263f894eebe3e491ad38c_e8f5e6608c36692de224583e0265c928.jpg",
    "type" : "image/jpeg",
    "bitrate" : 0,
    "duration" : 0,
    "title" : null,
    "properties" : null,
    "alternate" : [ {
      "href" : "https://i225.ntcdntempv26.com/data/images/72214/916633/029-93397d1.jpg?data=net",
      "type" : "image/jpeg",
      "bitrate" : 0,
      "duration" : 0,
      "title" : null,
      "properties" : null,
      "alternate" : null
    } ]
  }, {
    "href" : "https://raw.githubusercontent.com/quetcccd/comic_storage3/main/IMAGE/IMAGE_34b82a332a2ef91d16e4b69e0f5bca07_eeb5b77fb89263f894eebe3e491ad38c_0abda88dc29ee1286a6d0fddd332b323.jpg",
    "type" : "image/jpeg",
    "bitrate" : 0,
    "duration" : 0,
    "title" : null,
    "properties" : null,
    "alternate" : [ {
      "href" : "https://i225.ntcdntempv26.com/data/images/72214/916633/030-57a4864.jpg?data=net",
      "type" : "image/jpeg",
      "bitrate" : 0,
      "duration" : 0,
      "title" : null,
      "properties" : null,
      "alternate" : null
    } ]
  }, {
    "href" : "https://raw.githubusercontent.com/quetcccd/comic_storage3/main/IMAGE/IMAGE_34b82a332a2ef91d16e4b69e0f5bca07_eeb5b77fb89263f894eebe3e491ad38c_5e96cc01ac68d0ba322e3fd3d548faf6.jpg",
    "type" : "image/jpeg",
    "bitrate" : 0,
    "duration" : 0,
    "title" : null,
    "properties" : null,
    "alternate" : [ {
      "href" : "https://i225.ntcdntempv26.com/data/images/72214/916633/031-f83174b.jpg?data=net",
      "type" : "image/jpeg",
      "bitrate" : 0,
      "duration" : 0,
      "title" : null,
      "properties" : null,
      "alternate" : null
    } ]
  }, {
    "href" : "https://raw.githubusercontent.com/quetcccd/comic_storage3/main/IMAGE/IMAGE_34b82a332a2ef91d16e4b69e0f5bca07_eeb5b77fb89263f894eebe3e491ad38c_e63fbaf2393ae4970f1959a35948b415.jpg",
    "type" : "image/jpeg",
    "bitrate" : 0,
    "duration" : 0,
    "title" : null,
    "properties" : null,
    "alternate" : [ {
      "href" : "https://i225.ntcdntempv26.com/data/images/72214/916633/032-6636658.jpg?data=net",
      "type" : "image/jpeg",
      "bitrate" : 0,
      "duration" : 0,
      "title" : null,
      "properties" : null,
      "alternate" : null
    } ]
  }, {
    "href" : "https://raw.githubusercontent.com/quetcccd/comic_storage3/main/IMAGE/IMAGE_34b82a332a2ef91d16e4b69e0f5bca07_eeb5b77fb89263f894eebe3e491ad38c_2de96f1c265f0413f7a5b63d8a7d746b.jpg",
    "type" : "image/jpeg",
    "bitrate" : 0,
    "duration" : 0,
    "title" : null,
    "properties" : null,
    "alternate" : [ {
      "href" : "https://i225.ntcdntempv26.com/data/images/72214/916633/033-7b83177.jpg?data=net",
      "type" : "image/jpeg",
      "bitrate" : 0,
      "duration" : 0,
      "title" : null,
      "properties" : null,
      "alternate" : null
    } ]
  }, {
    "href" : "https://raw.githubusercontent.com/quetcccd/comic_storage3/main/IMAGE/IMAGE_34b82a332a2ef91d16e4b69e0f5bca07_eeb5b77fb89263f894eebe3e491ad38c_f8de184885c59f5214df709c517ab7b6.jpg",
    "type" : "image/jpeg",
    "bitrate" : 0,
    "duration" : 0,
    "title" : null,
    "properties" : null,
    "alternate" : [ {
      "href" : "https://i225.ntcdntempv26.com/data/images/72214/916633/034-434e6d0.jpg?data=net",
      "type" : "image/jpeg",
      "bitrate" : 0,
      "duration" : 0,
      "title" : null,
      "properties" : null,
      "alternate" : null
    } ]
  }, {
    "href" : "https://raw.githubusercontent.com/quetcccd/comic_storage3/main/IMAGE/IMAGE_34b82a332a2ef91d16e4b69e0f5bca07_eeb5b77fb89263f894eebe3e491ad38c_87ea7c453d1e0df3c93a2f5c9cc702dc.jpg",
    "type" : "image/jpeg",
    "bitrate" : 0,
    "duration" : 0,
    "title" : null,
    "properties" : null,
    "alternate" : [ {
      "href" : "https://i225.ntcdntempv26.com/data/images/72214/916633/035-318e828.jpg?data=net",
      "type" : "image/jpeg",
      "bitrate" : 0,
      "duration" : 0,
      "title" : null,
      "properties" : null,
      "alternate" : null
    } ]
  }, {
    "href" : "https://raw.githubusercontent.com/quetcccd/comic_storage3/main/IMAGE/IMAGE_34b82a332a2ef91d16e4b69e0f5bca07_eeb5b77fb89263f894eebe3e491ad38c_7b80ae9379ace69b1ebd03e72100ee18.jpg",
    "type" : "image/jpeg",
    "bitrate" : 0,
    "duration" : 0,
    "title" : null,
    "properties" : null,
    "alternate" : [ {
      "href" : "https://i225.ntcdntempv26.com/data/images/72214/916633/036-4248639.jpg?data=net",
      "type" : "image/jpeg",
      "bitrate" : 0,
      "duration" : 0,
      "title" : null,
      "properties" : null,
      "alternate" : null
    } ]
  }, {
    "href" : "https://raw.githubusercontent.com/quetcccd/comic_storage3/main/IMAGE/IMAGE_34b82a332a2ef91d16e4b69e0f5bca07_eeb5b77fb89263f894eebe3e491ad38c_9cc4b915407b3cf66125d6251280cd2f.jpg",
    "type" : "image/jpeg",
    "bitrate" : 0,
    "duration" : 0,
    "title" : null,
    "properties" : null,
    "alternate" : [ {
      "href" : "https://i225.ntcdntempv26.com/data/images/72214/916633/037-66ef057.jpg?data=net",
      "type" : "image/jpeg",
      "bitrate" : 0,
      "duration" : 0,
      "title" : null,
      "properties" : null,
      "alternate" : null
    } ]
  }, {
    "href" : "https://raw.githubusercontent.com/quetcccd/comic_storage3/main/IMAGE/IMAGE_34b82a332a2ef91d16e4b69e0f5bca07_eeb5b77fb89263f894eebe3e491ad38c_741ae013bcb6c01155419c7fb4441845.jpg",
    "type" : "image/jpeg",
    "bitrate" : 0,
    "duration" : 0,
    "title" : null,
    "properties" : null,
    "alternate" : [ {
      "href" : "https://i225.ntcdntempv26.com/data/images/72214/916633/038-3517650.jpg?data=net",
      "type" : "image/jpeg",
      "bitrate" : 0,
      "duration" : 0,
      "title" : null,
      "properties" : null,
      "alternate" : null
    } ]
  }, {
    "href" : "https://raw.githubusercontent.com/quetcccd/comic_storage3/main/IMAGE/IMAGE_34b82a332a2ef91d16e4b69e0f5bca07_eeb5b77fb89263f894eebe3e491ad38c_e00a2cf85e333befd317521cd99fad4a.jpg",
    "type" : "image/jpeg",
    "bitrate" : 0,
    "duration" : 0,
    "title" : null,
    "properties" : null,
    "alternate" : [ {
      "href" : "https://i225.ntcdntempv26.com/data/images/72214/916633/039-7f7a342.jpg?data=net",
      "type" : "image/jpeg",
      "bitrate" : 0,
      "duration" : 0,
      "title" : null,
      "properties" : null,
      "alternate" : null
    } ]
  }, {
    "href" : "https://raw.githubusercontent.com/quetcccd/comic_storage3/main/IMAGE/IMAGE_34b82a332a2ef91d16e4b69e0f5bca07_eeb5b77fb89263f894eebe3e491ad38c_fd93fba9556922f260a65924ff84f040.jpg",
    "type" : "image/jpeg",
    "bitrate" : 0,
    "duration" : 0,
    "title" : null,
    "properties" : null,
    "alternate" : [ {
      "href" : "https://i225.ntcdntempv26.com/data/images/72214/916633/040-6a004a5.jpg?data=net",
      "type" : "image/jpeg",
      "bitrate" : 0,
      "duration" : 0,
      "title" : null,
      "properties" : null,
      "alternate" : null
    } ]
  }, {
    "href" : "https://raw.githubusercontent.com/quetcccd/comic_storage3/main/IMAGE/IMAGE_34b82a332a2ef91d16e4b69e0f5bca07_eeb5b77fb89263f894eebe3e491ad38c_019eed09225d778e2a619ea89f65e93c.jpg",
    "type" : "image/jpeg",
    "bitrate" : 0,
    "duration" : 0,
    "title" : null,
    "properties" : null,
    "alternate" : [ {
      "href" : "https://i225.ntcdntempv26.com/data/images/72214/916633/041-db6c65f.jpg?data=net",
      "type" : "image/jpeg",
      "bitrate" : 0,
      "duration" : 0,
      "title" : null,
      "properties" : null,
      "alternate" : null
    } ]
  }, {
    "href" : "https://raw.githubusercontent.com/quetcccd/comic_storage3/main/IMAGE/IMAGE_34b82a332a2ef91d16e4b69e0f5bca07_eeb5b77fb89263f894eebe3e491ad38c_4f90403789cee7e73177105748387d12.jpg",
    "type" : "image/jpeg",
    "bitrate" : 0,
    "duration" : 0,
    "title" : null,
    "properties" : null,
    "alternate" : [ {
      "href" : "https://i225.ntcdntempv26.com/data/images/72214/916633/042-01c1fea.jpg?data=net",
      "type" : "image/jpeg",
      "bitrate" : 0,
      "duration" : 0,
      "title" : null,
      "properties" : null,
      "alternate" : null
    } ]
  }, {
    "href" : "https://raw.githubusercontent.com/quetcccd/comic_storage3/main/IMAGE/IMAGE_34b82a332a2ef91d16e4b69e0f5bca07_eeb5b77fb89263f894eebe3e491ad38c_8012189075dcfa83061b59820e6ce34b.jpg",
    "type" : "image/jpeg",
    "bitrate" : 0,
    "duration" : 0,
    "title" : null,
    "properties" : null,
    "alternate" : [ {
      "href" : "https://i225.ntcdntempv26.com/data/images/72214/916633/043-1308e11.jpg?data=net",
      "type" : "image/jpeg",
      "bitrate" : 0,
      "duration" : 0,
      "title" : null,
      "properties" : null,
      "alternate" : null
    } ]
  }, {
    "href" : "https://raw.githubusercontent.com/quetcccd/comic_storage3/main/IMAGE/IMAGE_34b82a332a2ef91d16e4b69e0f5bca07_eeb5b77fb89263f894eebe3e491ad38c_20f29fdb5672089c435db32a56295739.jpg",
    "type" : "image/jpeg",
    "bitrate" : 0,
    "duration" : 0,
    "title" : null,
    "properties" : null,
    "alternate" : [ {
      "href" : "https://i225.ntcdntempv26.com/data/images/72214/916633/044-98e035e.jpg?data=net",
      "type" : "image/jpeg",
      "bitrate" : 0,
      "duration" : 0,
      "title" : null,
      "properties" : null,
      "alternate" : null
    } ]
  }, {
    "href" : "https://raw.githubusercontent.com/quetcccd/comic_storage3/main/IMAGE/IMAGE_34b82a332a2ef91d16e4b69e0f5bca07_eeb5b77fb89263f894eebe3e491ad38c_b1475a35aab39b648c040da94c1d44f9.jpg",
    "type" : "image/jpeg",
    "bitrate" : 0,
    "duration" : 0,
    "title" : null,
    "properties" : null,
    "alternate" : [ {
      "href" : "https://i225.ntcdntempv26.com/data/images/72214/916633/045-b251bb4.jpg?data=net",
      "type" : "image/jpeg",
      "bitrate" : 0,
      "duration" : 0,
      "title" : null,
      "properties" : null,
      "alternate" : null
    } ]
  }, {
    "href" : "https://raw.githubusercontent.com/quetcccd/comic_storage3/main/IMAGE/IMAGE_34b82a332a2ef91d16e4b69e0f5bca07_eeb5b77fb89263f894eebe3e491ad38c_78c9e7d4e8288ee8785a33fa889b3b13.jpg",
    "type" : "image/jpeg",
    "bitrate" : 0,
    "duration" : 0,
    "title" : null,
    "properties" : null,
    "alternate" : [ {
      "href" : "https://i225.ntcdntempv26.com/data/images/72214/916633/046-4e57fb7.jpg?data=net",
      "type" : "image/jpeg",
      "bitrate" : 0,
      "duration" : 0,
      "title" : null,
      "properties" : null,
      "alternate" : null
    } ]
  }, {
    "href" : "https://raw.githubusercontent.com/quetcccd/comic_storage3/main/IMAGE/IMAGE_34b82a332a2ef91d16e4b69e0f5bca07_eeb5b77fb89263f894eebe3e491ad38c_ab410e3a0e459eb534dc729703ab0830.jpg",
    "type" : "image/jpeg",
    "bitrate" : 0,
    "duration" : 0,
    "title" : null,
    "properties" : null,
    "alternate" : [ {
      "href" : "https://i225.ntcdntempv26.com/data/images/72214/916633/047-e9e2758.jpg?data=net",
      "type" : "image/jpeg",
      "bitrate" : 0,
      "duration" : 0,
      "title" : null,
      "properties" : null,
      "alternate" : null
    } ]
  }, {
    "href" : "https://raw.githubusercontent.com/quetcccd/comic_storage3/main/IMAGE/IMAGE_34b82a332a2ef91d16e4b69e0f5bca07_eeb5b77fb89263f894eebe3e491ad38c_71148bd630defec87b235f1ef50df5d3.jpg",
    "type" : "image/jpeg",
    "bitrate" : 0,
    "duration" : 0,
    "title" : null,
    "properties" : null,
    "alternate" : [ {
      "href" : "https://i225.ntcdntempv26.com/data/images/72214/916633/048-b1c8d0e.jpg?data=net",
      "type" : "image/jpeg",
      "bitrate" : 0,
      "duration" : 0,
      "title" : null,
      "properties" : null,
      "alternate" : null
    } ]
  }, {
    "href" : "https://raw.githubusercontent.com/quetcccd/comic_storage3/main/IMAGE/IMAGE_34b82a332a2ef91d16e4b69e0f5bca07_eeb5b77fb89263f894eebe3e491ad38c_7c711c4f66c95a23c88c97622671fd75.jpg",
    "type" : "image/jpeg",
    "bitrate" : 0,
    "duration" : 0,
    "title" : null,
    "properties" : null,
    "alternate" : [ {
      "href" : "https://i225.ntcdntempv26.com/data/images/72214/916633/049-a00f02c.jpg?data=net",
      "type" : "image/jpeg",
      "bitrate" : 0,
      "duration" : 0,
      "title" : null,
      "properties" : null,
      "alternate" : null
    } ]
  }, {
    "href" : "https://raw.githubusercontent.com/quetcccd/comic_storage3/main/IMAGE/IMAGE_34b82a332a2ef91d16e4b69e0f5bca07_eeb5b77fb89263f894eebe3e491ad38c_90e42cb9bca66aded877fca65d476f3f.jpg",
    "type" : "image/jpeg",
    "bitrate" : 0,
    "duration" : 0,
    "title" : null,
    "properties" : null,
    "alternate" : [ {
      "href" : "https://i225.ntcdntempv26.com/data/images/72214/916633/050-e3da76e.jpg?data=net",
      "type" : "image/jpeg",
      "bitrate" : 0,
      "duration" : 0,
      "title" : null,
      "properties" : null,
      "alternate" : null
    } ]
  }, {
    "href" : "https://raw.githubusercontent.com/quetcccd/comic_storage3/main/IMAGE/IMAGE_34b82a332a2ef91d16e4b69e0f5bca07_eeb5b77fb89263f894eebe3e491ad38c_bdbce776039c605e763eaecc6653837e.jpg",
    "type" : "image/jpeg",
    "bitrate" : 0,
    "duration" : 0,
    "title" : null,
    "properties" : null,
    "alternate" : [ {
      "href" : "https://i225.ntcdntempv26.com/data/images/72214/916633/051-253f691.jpg?data=net",
      "type" : "image/jpeg",
      "bitrate" : 0,
      "duration" : 0,
      "title" : null,
      "properties" : null,
      "alternate" : null
    } ]
  }, {
    "href" : "https://raw.githubusercontent.com/quetcccd/comic_storage3/main/IMAGE/IMAGE_34b82a332a2ef91d16e4b69e0f5bca07_eeb5b77fb89263f894eebe3e491ad38c_d1ece1303528e1cfb29ccb8537e35f6e.jpg",
    "type" : "image/jpeg",
    "bitrate" : 0,
    "duration" : 0,
    "title" : null,
    "properties" : null,
    "alternate" : [ {
      "href" : "https://i225.ntcdntempv26.com/data/images/72214/916633/052-0b9bd8b.jpg?data=net",
      "type" : "image/jpeg",
      "bitrate" : 0,
      "duration" : 0,
      "title" : null,
      "properties" : null,
      "alternate" : null
    } ]
  }, {
    "href" : "https://raw.githubusercontent.com/quetcccd/comic_storage3/main/IMAGE/IMAGE_34b82a332a2ef91d16e4b69e0f5bca07_eeb5b77fb89263f894eebe3e491ad38c_9fa5f453f9f241133e0a67105b013ddb.jpg",
    "type" : "image/jpeg",
    "bitrate" : 0,
    "duration" : 0,
    "title" : null,
    "properties" : null,
    "alternate" : [ {
      "href" : "https://i225.ntcdntempv26.com/data/images/72214/916633/053-8223685.jpg?data=net",
      "type" : "image/jpeg",
      "bitrate" : 0,
      "duration" : 0,
      "title" : null,
      "properties" : null,
      "alternate" : null
    } ]
  }, {
    "href" : "https://raw.githubusercontent.com/quetcccd/comic_storage3/main/IMAGE/IMAGE_34b82a332a2ef91d16e4b69e0f5bca07_eeb5b77fb89263f894eebe3e491ad38c_ce4802dd7d70e907e3ba9667706897b3.jpg",
    "type" : "image/jpeg",
    "bitrate" : 0,
    "duration" : 0,
    "title" : null,
    "properties" : null,
    "alternate" : [ {
      "href" : "https://i225.ntcdntempv26.com/data/images/72214/916633/054-7b4dfc9.jpg?data=net",
      "type" : "image/jpeg",
      "bitrate" : 0,
      "duration" : 0,
      "title" : null,
      "properties" : null,
      "alternate" : null
    } ]
  }, {
    "href" : "https://raw.githubusercontent.com/quetcccd/comic_storage3/main/IMAGE/IMAGE_34b82a332a2ef91d16e4b69e0f5bca07_eeb5b77fb89263f894eebe3e491ad38c_ba7b8fbf04f42cbeb9d3fc57b7e14fa5.jpg",
    "type" : "image/jpeg",
    "bitrate" : 0,
    "duration" : 0,
    "title" : null,
    "properties" : null,
    "alternate" : [ {
      "href" : "https://i225.ntcdntempv26.com/data/images/72214/916633/055-032fc53.jpg?data=net",
      "type" : "image/jpeg",
      "bitrate" : 0,
      "duration" : 0,
      "title" : null,
      "properties" : null,
      "alternate" : null
    } ]
  }, {
    "href" : "https://raw.githubusercontent.com/quetcccd/comic_storage3/main/IMAGE/IMAGE_34b82a332a2ef91d16e4b69e0f5bca07_eeb5b77fb89263f894eebe3e491ad38c_40be2907296f79d36fa9566e52293965.jpg",
    "type" : "image/jpeg",
    "bitrate" : 0,
    "duration" : 0,
    "title" : null,
    "properties" : null,
    "alternate" : [ {
      "href" : "https://i225.ntcdntempv26.com/data/images/72214/916633/056-dccdf33.jpg?data=net",
      "type" : "image/jpeg",
      "bitrate" : 0,
      "duration" : 0,
      "title" : null,
      "properties" : null,
      "alternate" : null
    } ]
  }, {
    "href" : "https://raw.githubusercontent.com/quetcccd/comic_storage3/main/IMAGE/IMAGE_34b82a332a2ef91d16e4b69e0f5bca07_eeb5b77fb89263f894eebe3e491ad38c_8d1e541087aacf18c02557f4f274efc3.jpg",
    "type" : "image/jpeg",
    "bitrate" : 0,
    "duration" : 0,
    "title" : null,
    "properties" : null,
    "alternate" : [ {
      "href" : "https://i225.ntcdntempv26.com/data/images/72214/916633/057-f237494.jpg?data=net",
      "type" : "image/jpeg",
      "bitrate" : 0,
      "duration" : 0,
      "title" : null,
      "properties" : null,
      "alternate" : null
    } ]
  }, {
    "href" : "https://raw.githubusercontent.com/quetcccd/comic_storage3/main/IMAGE/IMAGE_34b82a332a2ef91d16e4b69e0f5bca07_eeb5b77fb89263f894eebe3e491ad38c_c607ba52d6b48ad984794cb1e3a53627.jpg",
    "type" : "image/jpeg",
    "bitrate" : 0,
    "duration" : 0,
    "title" : null,
    "properties" : null,
    "alternate" : [ {
      "href" : "https://i225.ntcdntempv26.com/data/images/72214/916633/058-1fca5c7.jpg?data=net",
      "type" : "image/jpeg",
      "bitrate" : 0,
      "duration" : 0,
      "title" : null,
      "properties" : null,
      "alternate" : null
    } ]
  }, {
    "href" : "https://raw.githubusercontent.com/quetcccd/comic_storage3/main/IMAGE/IMAGE_34b82a332a2ef91d16e4b69e0f5bca07_eeb5b77fb89263f894eebe3e491ad38c_af145230c4efb6e23a59d50919e4f479.jpg",
    "type" : "image/jpeg",
    "bitrate" : 0,
    "duration" : 0,
    "title" : null,
    "properties" : null,
    "alternate" : [ {
      "href" : "https://i225.ntcdntempv26.com/data/images/72214/916633/059-8624adf.jpg?data=net",
      "type" : "image/jpeg",
      "bitrate" : 0,
      "duration" : 0,
      "title" : null,
      "properties" : null,
      "alternate" : null
    } ]
  }, {
    "href" : "https://raw.githubusercontent.com/quetcccd/comic_storage3/main/IMAGE/IMAGE_34b82a332a2ef91d16e4b69e0f5bca07_eeb5b77fb89263f894eebe3e491ad38c_34404dfa6ab1a9ab6eb8b3821b9c67cc.jpg",
    "type" : "image/jpeg",
    "bitrate" : 0,
    "duration" : 0,
    "title" : null,
    "properties" : null,
    "alternate" : [ {
      "href" : "https://i225.ntcdntempv26.com/data/images/72214/916633/060-5dc564f.jpg?data=net",
      "type" : "image/jpeg",
      "bitrate" : 0,
      "duration" : 0,
      "title" : null,
      "properties" : null,
      "alternate" : null
    } ]
  }, {
    "href" : "https://raw.githubusercontent.com/quetcccd/comic_storage3/main/IMAGE/IMAGE_34b82a332a2ef91d16e4b69e0f5bca07_eeb5b77fb89263f894eebe3e491ad38c_8cace0cc3ce22cbc9b466eabe5d45961.jpg",
    "type" : "image/jpeg",
    "bitrate" : 0,
    "duration" : 0,
    "title" : null,
    "properties" : null,
    "alternate" : [ {
      "href" : "https://i225.ntcdntempv26.com/data/images/72214/916633/061-a8fbbd8.jpg?data=net",
      "type" : "image/jpeg",
      "bitrate" : 0,
      "duration" : 0,
      "title" : null,
      "properties" : null,
      "alternate" : null
    } ]
  } ],
  "toc" : null,
  "@context" : "https://readium.org/webpub-manifest/context.jsonld"
}