{
  "metadata" : {
    "identifier" : "https://www.nettruyento.com/truyen-tranh/danh-mon-chi-ai-240592",
    "title" : "Danh Môn Chí Ái - Chapter 80.1",
    "subtitle" : null,
    "author" : null,
    "narrator" : null,
    "language" : "vi",
    "description" : null,
    "publisher" : "N/A",
    "subject" : null,
    "modified" : null,
    "published" : "2023-06-10",
    "duration" : 0,
    "abridged" : false,
    "conformsTo" : "https://readium.org/webpub-manifest/profiles/divina",
    "numberOfPages" : 578,
    "readingProgression" : "ttb",
    "belongsTo" : null,
    "presentation" : {
      "fit" : "width",
      "overflow" : "scrolled",
      "continuous" : true
    },
    "@type" : null,
    "schema:license" : null
  },
  "links" : [ {
    "rel" : "self",
    "href" : "https://raw.githubusercontent.com/thuvienonline40/book_storage_collection/main/comic_manifest.json",
    "type" : "application/divina+json"
  } ],
  "readingOrder" : [ {
    "href" : "https://raw.githubusercontent.com/tsvhcomic23/comic_storage3/main/IMAGE/IMAGE_89f7a0eb61192888bbeb51caa2ecdf10_355354623594138a864f19a3633be726_5faf8825886ea9b12e119fcc7d07e12f.jpg",
    "type" : "image/jpeg",
    "bitrate" : 0,
    "duration" : 0,
    "title" : null,
    "properties" : null,
    "alternate" : [ {
      "href" : "https://i332.ntcdntempv26.com/data/images/24059/542281/001-fix.jpg?data=net",
      "type" : "image/jpeg",
      "bitrate" : 0,
      "duration" : 0,
      "title" : null,
      "properties" : null,
      "alternate" : null
    } ]
  }, {
    "href" : "https://raw.githubusercontent.com/tsvhcomic23/comic_storage3/main/IMAGE/IMAGE_89f7a0eb61192888bbeb51caa2ecdf10_355354623594138a864f19a3633be726_4a483f4aaf6b47aa864f7a682b407f0a.jpg",
    "type" : "image/jpeg",
    "bitrate" : 0,
    "duration" : 0,
    "title" : null,
    "properties" : null,
    "alternate" : [ {
      "href" : "https://i332.ntcdntempv26.com/data/images/24059/542281/002-fix.jpg?data=net",
      "type" : "image/jpeg",
      "bitrate" : 0,
      "duration" : 0,
      "title" : null,
      "properties" : null,
      "alternate" : null
    } ]
  }, {
    "href" : "https://raw.githubusercontent.com/tsvhcomic23/comic_storage3/main/IMAGE/IMAGE_89f7a0eb61192888bbeb51caa2ecdf10_355354623594138a864f19a3633be726_43ca3963e2c4c3125b48a20117b66c93.jpg",
    "type" : "image/jpeg",
    "bitrate" : 0,
    "duration" : 0,
    "title" : null,
    "properties" : null,
    "alternate" : [ {
      "href" : "https://i332.ntcdntempv26.com/data/images/24059/542281/003-fix.jpg?data=net",
      "type" : "image/jpeg",
      "bitrate" : 0,
      "duration" : 0,
      "title" : null,
      "properties" : null,
      "alternate" : null
    } ]
  }, {
    "href" : "https://raw.githubusercontent.com/tsvhcomic23/comic_storage3/main/IMAGE/IMAGE_89f7a0eb61192888bbeb51caa2ecdf10_355354623594138a864f19a3633be726_1006dc006e17a0e3ea3d1d9ba35ad2a3.jpg",
    "type" : "image/jpeg",
    "bitrate" : 0,
    "duration" : 0,
    "title" : null,
    "properties" : null,
    "alternate" : [ {
      "href" : "https://i332.ntcdntempv26.com/data/images/24059/542281/004-fix.jpg?data=net",
      "type" : "image/jpeg",
      "bitrate" : 0,
      "duration" : 0,
      "title" : null,
      "properties" : null,
      "alternate" : null
    } ]
  }, {
    "href" : "https://raw.githubusercontent.com/tsvhcomic23/comic_storage3/main/IMAGE/IMAGE_89f7a0eb61192888bbeb51caa2ecdf10_355354623594138a864f19a3633be726_a6c4a02c8ee87212ffce1835724987df.jpg",
    "type" : "image/jpeg",
    "bitrate" : 0,
    "duration" : 0,
    "title" : null,
    "properties" : null,
    "alternate" : [ {
      "href" : "https://i332.ntcdntempv26.com/data/images/24059/542281/005-fix.jpg?data=net",
      "type" : "image/jpeg",
      "bitrate" : 0,
      "duration" : 0,
      "title" : null,
      "properties" : null,
      "alternate" : null
    } ]
  }, {
    "href" : "https://raw.githubusercontent.com/tsvhcomic23/comic_storage3/main/IMAGE/IMAGE_89f7a0eb61192888bbeb51caa2ecdf10_355354623594138a864f19a3633be726_26b1f36d34a625e8ffd6d59407f25b9b.jpg",
    "type" : "image/jpeg",
    "bitrate" : 0,
    "duration" : 0,
    "title" : null,
    "properties" : null,
    "alternate" : [ {
      "href" : "https://i332.ntcdntempv26.com/data/images/24059/542281/006-fix.jpg?data=net",
      "type" : "image/jpeg",
      "bitrate" : 0,
      "duration" : 0,
      "title" : null,
      "properties" : null,
      "alternate" : null
    } ]
  }, {
    "href" : "https://raw.githubusercontent.com/tsvhcomic23/comic_storage3/main/IMAGE/IMAGE_89f7a0eb61192888bbeb51caa2ecdf10_355354623594138a864f19a3633be726_57f163575b80dd55db898b55efadd030.jpg",
    "type" : "image/jpeg",
    "bitrate" : 0,
    "duration" : 0,
    "title" : null,
    "properties" : null,
    "alternate" : [ {
      "href" : "https://i332.ntcdntempv26.com/data/images/24059/542281/007-fix.jpg?data=net",
      "type" : "image/jpeg",
      "bitrate" : 0,
      "duration" : 0,
      "title" : null,
      "properties" : null,
      "alternate" : null
    } ]
  }, {
    "href" : "https://raw.githubusercontent.com/tsvhcomic23/comic_storage3/main/IMAGE/IMAGE_89f7a0eb61192888bbeb51caa2ecdf10_355354623594138a864f19a3633be726_95b1c8db2c40a6f13d30010bb3abfc60.jpg",
    "type" : "image/jpeg",
    "bitrate" : 0,
    "duration" : 0,
    "title" : null,
    "properties" : null,
    "alternate" : [ {
      "href" : "https://i332.ntcdntempv26.com/data/images/24059/542281/008-fix.jpg?data=net",
      "type" : "image/jpeg",
      "bitrate" : 0,
      "duration" : 0,
      "title" : null,
      "properties" : null,
      "alternate" : null
    } ]
  }, {
    "href" : "https://raw.githubusercontent.com/tsvhcomic23/comic_storage3/main/IMAGE/IMAGE_89f7a0eb61192888bbeb51caa2ecdf10_355354623594138a864f19a3633be726_69eb47f976dd72c1cf1d9db0da687f54.jpg",
    "type" : "image/jpeg",
    "bitrate" : 0,
    "duration" : 0,
    "title" : null,
    "properties" : null,
    "alternate" : [ {
      "href" : "https://i332.ntcdntempv26.com/data/images/24059/542281/009-fix.jpg?data=net",
      "type" : "image/jpeg",
      "bitrate" : 0,
      "duration" : 0,
      "title" : null,
      "properties" : null,
      "alternate" : null
    } ]
  }, {
    "href" : "https://raw.githubusercontent.com/tsvhcomic23/comic_storage3/main/IMAGE/IMAGE_89f7a0eb61192888bbeb51caa2ecdf10_355354623594138a864f19a3633be726_ccb404f9cbe79588baad74d13bde1ed3.jpg",
    "type" : "image/jpeg",
    "bitrate" : 0,
    "duration" : 0,
    "title" : null,
    "properties" : null,
    "alternate" : [ {
      "href" : "https://i332.ntcdntempv26.com/data/images/24059/542281/010-fix.jpg?data=net",
      "type" : "image/jpeg",
      "bitrate" : 0,
      "duration" : 0,
      "title" : null,
      "properties" : null,
      "alternate" : null
    } ]
  }, {
    "href" : "https://raw.githubusercontent.com/tsvhcomic23/comic_storage3/main/IMAGE/IMAGE_89f7a0eb61192888bbeb51caa2ecdf10_355354623594138a864f19a3633be726_3debe1cf0edf4382764114606daba212.jpg",
    "type" : "image/jpeg",
    "bitrate" : 0,
    "duration" : 0,
    "title" : null,
    "properties" : null,
    "alternate" : [ {
      "href" : "https://i332.ntcdntempv26.com/data/images/24059/542281/011-fix.jpg?data=net",
      "type" : "image/jpeg",
      "bitrate" : 0,
      "duration" : 0,
      "title" : null,
      "properties" : null,
      "alternate" : null
    } ]
  }, {
    "href" : "https://raw.githubusercontent.com/tsvhcomic23/comic_storage3/main/IMAGE/IMAGE_89f7a0eb61192888bbeb51caa2ecdf10_355354623594138a864f19a3633be726_e6ad35c66f5e5e0ec9cb7d16121004ae.jpg",
    "type" : "image/jpeg",
    "bitrate" : 0,
    "duration" : 0,
    "title" : null,
    "properties" : null,
    "alternate" : [ {
      "href" : "https://i332.ntcdntempv26.com/data/images/24059/542281/012-fix.jpg?data=net",
      "type" : "image/jpeg",
      "bitrate" : 0,
      "duration" : 0,
      "title" : null,
      "properties" : null,
      "alternate" : null
    } ]
  }, {
    "href" : "https://raw.githubusercontent.com/tsvhcomic23/comic_storage3/main/IMAGE/IMAGE_89f7a0eb61192888bbeb51caa2ecdf10_355354623594138a864f19a3633be726_4e0b4635c6f3ab3d43aa8f3dd7587328.jpg",
    "type" : "image/jpeg",
    "bitrate" : 0,
    "duration" : 0,
    "title" : null,
    "properties" : null,
    "alternate" : [ {
      "href" : "https://i332.ntcdntempv26.com/data/images/24059/542281/013-fix.jpg?data=net",
      "type" : "image/jpeg",
      "bitrate" : 0,
      "duration" : 0,
      "title" : null,
      "properties" : null,
      "alternate" : null
    } ]
  }, {
    "href" : "https://raw.githubusercontent.com/tsvhcomic23/comic_storage3/main/IMAGE/IMAGE_89f7a0eb61192888bbeb51caa2ecdf10_355354623594138a864f19a3633be726_f3ee1952898657f8cea3e422efce62db.jpg",
    "type" : "image/jpeg",
    "bitrate" : 0,
    "duration" : 0,
    "title" : null,
    "properties" : null,
    "alternate" : [ {
      "href" : "https://i332.ntcdntempv26.com/data/images/24059/542281/014-fix.jpg?data=net",
      "type" : "image/jpeg",
      "bitrate" : 0,
      "duration" : 0,
      "title" : null,
      "properties" : null,
      "alternate" : null
    } ]
  }, {
    "href" : "https://raw.githubusercontent.com/tsvhcomic23/comic_storage3/main/IMAGE/IMAGE_89f7a0eb61192888bbeb51caa2ecdf10_355354623594138a864f19a3633be726_6889e2b90d30154ad993fe67af98f75b.jpg",
    "type" : "image/jpeg",
    "bitrate" : 0,
    "duration" : 0,
    "title" : null,
    "properties" : null,
    "alternate" : [ {
      "href" : "https://i332.ntcdntempv26.com/data/images/24059/542281/015-fix.jpg?data=net",
      "type" : "image/jpeg",
      "bitrate" : 0,
      "duration" : 0,
      "title" : null,
      "properties" : null,
      "alternate" : null
    } ]
  }, {
    "href" : "https://raw.githubusercontent.com/tsvhcomic23/comic_storage3/main/IMAGE/IMAGE_89f7a0eb61192888bbeb51caa2ecdf10_355354623594138a864f19a3633be726_ef029a83adc0956a1455ac33fe9eeece.jpg",
    "type" : "image/jpeg",
    "bitrate" : 0,
    "duration" : 0,
    "title" : null,
    "properties" : null,
    "alternate" : [ {
      "href" : "https://i332.ntcdntempv26.com/data/images/24059/542281/016-fix.jpg?data=net",
      "type" : "image/jpeg",
      "bitrate" : 0,
      "duration" : 0,
      "title" : null,
      "properties" : null,
      "alternate" : null
    } ]
  }, {
    "href" : "https://raw.githubusercontent.com/tsvhcomic23/comic_storage3/main/IMAGE/IMAGE_89f7a0eb61192888bbeb51caa2ecdf10_355354623594138a864f19a3633be726_0d13d15e4e7f08bd8e2bfd74e71f3527.jpg",
    "type" : "image/jpeg",
    "bitrate" : 0,
    "duration" : 0,
    "title" : null,
    "properties" : null,
    "alternate" : [ {
      "href" : "https://i332.ntcdntempv26.com/data/images/24059/542281/017-fix.jpg?data=net",
      "type" : "image/jpeg",
      "bitrate" : 0,
      "duration" : 0,
      "title" : null,
      "properties" : null,
      "alternate" : null
    } ]
  }, {
    "href" : "https://raw.githubusercontent.com/tsvhcomic23/comic_storage3/main/IMAGE/IMAGE_89f7a0eb61192888bbeb51caa2ecdf10_355354623594138a864f19a3633be726_de4b3704516ec42a1694342e054e2e3f.jpg",
    "type" : "image/jpeg",
    "bitrate" : 0,
    "duration" : 0,
    "title" : null,
    "properties" : null,
    "alternate" : [ {
      "href" : "https://i332.ntcdntempv26.com/data/images/24059/542281/018-fix.jpg?data=net",
      "type" : "image/jpeg",
      "bitrate" : 0,
      "duration" : 0,
      "title" : null,
      "properties" : null,
      "alternate" : null
    } ]
  } ],
  "toc" : null,
  "@context" : "https://readium.org/webpub-manifest/context.jsonld"
}